credvault_cie-1.1.0.dist-info/licenses/LICENSE
credvault_utils/__init__.py
credvault_utils/device.py
credvault_cie-1.1.0.dist-info/METADATA
credvault_cie-1.1.0.dist-info/WHEEL
credvault_cie-1.1.0.dist-info/top_level.txt
credvault_cie-1.1.0.dist-info/RECORD
