Metadata-Version: 2.4
Name: credvault-cie
Version: 1.1.0
Summary: CredVault Intelligence Engine (CIE) - CLI utilities for AI/ML operations and IoT Device SDK
Author-email: Samuel Mbugua <mrsamuelmbugua908@gmail.com>
License: ISC
Project-URL: Homepage, https://credvault.io
Project-URL: Repository, https://github.com/CREDVAULT-LTD/CredVault-DB
Project-URL: Issues, https://github.com/CREDVAULT-LTD/CredVault-DB/issues
Keywords: credvault,cie,cli,ai,ml,iot,device,telemetry
Classifier: Development Status :: 4 - Beta
Classifier: Intended Audience :: Developers
Classifier: License :: OSI Approved :: ISC License (ISCL)
Classifier: Programming Language :: Python :: 3
Classifier: Programming Language :: Python :: 3.10
Classifier: Programming Language :: Python :: 3.11
Classifier: Programming Language :: Python :: 3.12
Classifier: Programming Language :: Python :: 3.13
Requires-Python: >=3.10
License-File: LICENSE
Requires-Dist: requests>=2.28.0
Dynamic: license-file
